random_uk_bank_account/__init__.py
random_uk_bank_account/client/__init__.py
random_uk_bank_account/client/sqlite3.py
random_uk_bank_account/client/vocalink.py
random_uk_bank_account/generator/__init__.py
random_uk_bank_account/generator/uk_account.py
random_uk_bank_account/utils/__init__.py
random_uk_bank_account/utils/config.py
random_uk_bank_account/utils/exceptions.py
random_uk_bank_account/utils/number.py
random_uk_bank_account/utils/random.py
random_uk_bank_account/utils/validators.py
random_uk_bank_account/validator/__init__.py
random_uk_bank_account/validator/modulus_checker.py
random_uk_bank_account/validator/vocalink_check_logic.py
random_uk_bank_account/vocalink/__init__.py
random_uk_bank_account/vocalink/vocalink.py
random_uk_bank_account/vocalink/vocalink_data.py
random_uk_bank_account/vocalink/vocalink_db.py
random_uk_bank_account/vocalink/vocalink_db_init.py
random_uk_bank_account/vocalink/vocalink_model.py
random_uk_bank_account/vocalink/vocalink_version.py
random_uk_bank_account-0.0.5.dist-info/LICENSE
random_uk_bank_account-0.0.5.dist-info/METADATA
random_uk_bank_account-0.0.5.dist-info/WHEEL
random_uk_bank_account-0.0.5.dist-info/top_level.txt
random_uk_bank_account-0.0.5.dist-info/RECORD
