Metadata-Version: 2.1
Name: random-uk-bank-account
Version: 0.0.5
Summary: Random UK Bank Account Generator
Home-page: https://github.com/j-puri/random-uk-bank-account
Author: j.puri
Author-email: j-puri.github@outlook.com
Classifier: Programming Language :: Python :: 3.7
Classifier: Programming Language :: Python :: 3.8
Classifier: Programming Language :: Python :: 3.9
Classifier: Programming Language :: Python :: 3.10
Classifier: Programming Language :: Python :: 3.11
Classifier: Programming Language :: Python :: 3.12
Classifier: License :: OSI Approved :: MIT License
Classifier: Operating System :: OS Independent
License-File: LICENSE
Requires-Dist: requests >=2.25.1
Requires-Dist: dataclasses-json >=0.5.2
Requires-Dist: urllib3 >=1.26.4
Requires-Dist: beautifulsoup4 >=4.10.0
